ml_runlog/__init__.py
ml_runlog/main.py
ml_runlog-2.2.dist-info/LICENSE
ml_runlog-2.2.dist-info/METADATA
ml_runlog-2.2.dist-info/WHEEL
ml_runlog-2.2.dist-info/top_level.txt
ml_runlog-2.2.dist-info/RECORD
